bunt/__init__.py
bunt/config.py
bunt/environment.py
bunt/exceptions.py
bunt/hop.py
bunt/wrapper.py
bunt/containers/__init__.py
bunt/containers/configuration.py
bunt/containers/connectable.py
bunt/containers/health.py
bunt/containers/http.py
bunt/containers/rest.py
bunt-0.0.2.data/scripts/bunt
bunt-0.0.2.dist-info/LICENSE
bunt-0.0.2.dist-info/METADATA
bunt-0.0.2.dist-info/WHEEL
bunt-0.0.2.dist-info/top_level.txt
bunt-0.0.2.dist-info/RECORD
