Metadata-Version: 2.1
Name: bunt
Version: 0.0.2
Summary: UNKNOWN
Home-page: UNKNOWN
Author: UNKNOWN
Author-email: UNKNOWN
License: UNKNOWN
Platform: UNKNOWN
Requires-Dist: docker (==4.1.0)
